odoo10_addon_product_secondary_unit-10.0.1.0.1-nspkg.pth
odoo/addons/product_secondary_unit/README.rst
odoo/addons/product_secondary_unit/__init__.py
odoo/addons/product_secondary_unit/__manifest__.py
odoo/addons/product_secondary_unit/i18n/es.po
odoo/addons/product_secondary_unit/i18n/fr.po
odoo/addons/product_secondary_unit/i18n/product_secondary_unit.pot
odoo/addons/product_secondary_unit/i18n/zh_CN.po
odoo/addons/product_secondary_unit/models/__init__.py
odoo/addons/product_secondary_unit/models/product_second_unit.py
odoo/addons/product_secondary_unit/models/product_template.py
odoo/addons/product_secondary_unit/readme/CONTRIBUTORS.rst
odoo/addons/product_secondary_unit/readme/DESCRIPTION.rst
odoo/addons/product_secondary_unit/readme/USAGE.rst
odoo/addons/product_secondary_unit/security/ir.model.access.csv
odoo/addons/product_secondary_unit/static/description/icon.png
odoo/addons/product_secondary_unit/static/description/index.html
odoo/addons/product_secondary_unit/tests/__init__.py
odoo/addons/product_secondary_unit/tests/test_product_second_unit.py
odoo/addons/product_secondary_unit/views/product_views.xml
odoo10_addon_product_secondary_unit-10.0.1.0.1.dist-info/METADATA
odoo10_addon_product_secondary_unit-10.0.1.0.1.dist-info/WHEEL
odoo10_addon_product_secondary_unit-10.0.1.0.1.dist-info/namespace_packages.txt
odoo10_addon_product_secondary_unit-10.0.1.0.1.dist-info/top_level.txt
odoo10_addon_product_secondary_unit-10.0.1.0.1.dist-info/RECORD
