Metadata-Version: 2.1
Name: odoo10-addon-product-secondary-unit
Version: 10.0.1.0.1
Summary: Set a secondary unit per product
Home-page: https://github.com/OCA/product-attribute
Author: Tecnativa, Odoo Community Association (OCA)
Author-email: support@odoo-community.org
License: AGPL-3
Platform: UNKNOWN
Classifier: Programming Language :: Python
Classifier: Framework :: Odoo
Classifier: License :: OSI Approved :: GNU Affero General Public License v3
Classifier: Development Status :: 4 - Beta
Requires-Python: ~=2.7
Requires-Dist: odoo (<10.1dev,>=10.0)
